deche/__init__.py
deche/core.py
deche/inspection.py
deche/test_utils/__init__.py
deche/util.py
deche/validators.py
deche-0.10.0.dist-info/METADATA
deche-0.10.0.dist-info/WHEEL
deche-0.10.0.dist-info/RECORD
