Metadata-Version: 2.1
Name: deche
Version: 0.10.0
Summary: 
Author: Bradley McElroy
Author-email: bradley.mcelroy@live.com
Requires-Python: >=3.9,<4.0
Classifier: Programming Language :: Python :: 3
Classifier: Programming Language :: Python :: 3.9
Classifier: Programming Language :: Python :: 3.10
Classifier: Programming Language :: Python :: 3.11
Classifier: Programming Language :: Python :: 3.12
Provides-Extra: s3
Requires-Dist: cloudpickle (>=2.0.0)
Requires-Dist: fsspec (>=2021.10.1)
Requires-Dist: s3fs (>=2021.7.0) ; extra == "s3"
